{
  "appKey": "",
  "appSecret": "",
  "excludeScenes": [],
  "includeAnySDK": false,
  "includeSDKBox": false,
  "includeSdk": [
    "anysdk"
  ],
  "inlineSpriteFrames": true,
  "inlineSpriteFrames_native": true,
  "mergeStartScene": false,
  "oauthLoginServer": "",
  "optimizeHotUpdate": false,
  "orientation": {
    "landscapeLeft": true,
    "landscapeRight": true,
    "portrait": false,
    "upsideDown": false
  },
  "packageName": "org.cocos2d.helloworld",
  "privateKey": "",
  "renderMode": "0",
  "startScene": "e316f0c2-7cb4-4687-8ae2-6c09b9deff2f",
  "title": "hello_world",
  "webOrientation": "auto"
}